gold_dl/__init__.py
gold_dl/__main__.py
gold_dl/cli.py
gold_dl/utils.py
gold_dl/handlers/PlaylistHandler.py
gold_dl/handlers/URLHandler.py
gold_dl/handlers/__init__.py
gold_dl/services/AudioService.py
gold_dl/services/DownloadService.py
gold_dl/services/FileService.py
gold_dl/services/VideoService.py
gold_dl/services/__init__.py
gold_dl/tests/__init__.py
gold_dl/tests/test_utils.py
gold_dl-2026.1.20.2.dist-info/licenses/LICENSE
gold_dl-2026.1.20.2.dist-info/METADATA
gold_dl-2026.1.20.2.dist-info/WHEEL
gold_dl-2026.1.20.2.dist-info/entry_points.txt
gold_dl-2026.1.20.2.dist-info/top_level.txt
gold_dl-2026.1.20.2.dist-info/RECORD
