Metadata-Version: 2.4
Name: gold-dl
Version: 2026.1.20.2
Summary: Library GoLD YouTube downloader (video / audio / shorts / playlists) with smart caching and auto quality handling
Author: VOLT5775
Author-email: VOLT5775@users.noreply.github.com
License: MIT
Project-URL: Homepage, https://github.com/VOLT5775/VoLTGoLD-YT
Project-URL: Source Code, https://github.com/VOLT5775/VoLTGoLD-YT
Project-URL: Bug Tracker, https://github.com/VOLT5775/VoLTGoLD-YT/issues
Project-URL: Documentation, https://github.com/VOLT5775/VoLTGoLD-YT
Project-URL: Author, https://github.com/VOLT5775
Keywords: youtube,download,downloader,telegram,telegram-streamcli,gold-dl,voltgold,yt-downloader,pytubefix,pytube,youtube-dl
Platform: Linux
Platform: Windows
Platform: MacOS
Classifier: License :: OSI Approved :: MIT License
Classifier: Operating System :: OS Independent
Classifier: Programming Language :: Python :: 3.9
Classifier: Programming Language :: Python :: 3.10
Classifier: Programming Language :: Python :: 3.11
Classifier: Programming Language :: Python :: 3.12
Classifier: Programming Language :: Python :: 3.13
Classifier: Topic :: Multimedia :: Video
Classifier: Topic :: Utilities
Requires-Python: >=3.6
License-File: LICENSE
Requires-Dist: pytubefix>=0.4.0
Requires-Dist: inquirer>=3.0.0
Requires-Dist: yaspin>=3.0.0
Requires-Dist: typer>=0.9.0
Requires-Dist: requests>=2.28.0
Requires-Dist: rich>=13.0.0
Requires-Dist: termcolor>=2.0.0
Requires-Dist: moviepy>=1.0.0
Requires-Dist: questionary
Dynamic: author
Dynamic: author-email
Dynamic: classifier
Dynamic: description
Dynamic: description-content-type
Dynamic: keywords
Dynamic: license
Dynamic: license-file
Dynamic: platform
Dynamic: project-url
Dynamic: requires-dist
Dynamic: requires-python
Dynamic: summary
